{"cameraMode":{"drawMode":0,"name":"Shaded","section":"Shading Mode"},"sceneLighting":true,"audioPlay":false,"sceneViewState":{"m_AlwaysRefresh":false,"showFog":true,"showSkybox":true,"showFlares":true,"showImageEffects":true,"showParticleSystems":true,"showVisualEffectGraphs":true,"m_FxEnabled":true},"in2DMode":false,"pivot":{"x":-34.79718017578125,"y":-10.10220718383789,"z":17.248640060424806},"rotation":{"x":-0.1427285522222519,"y":-0.37373611330986025,"z":0.0583602674305439,"w":-0.9146679639816284},"size":14.780885696411133,"orthographic":false}